{"trial_id": "017", "hyperparameters": {"space": [{"class_name": "Float", "config": {"name": "indrop", "default": 0.1, "conditions": [], "min_value": 0.1, "max_value": 0.3, "step": null, "sampling": "log"}}, {"class_name": "Int", "config": {"name": "inner_layers", "default": null, "conditions": [], "min_value": 1, "max_value": 3, "step": 1, "sampling": "linear"}}, {"class_name": "Int", "config": {"name": "inner_neurons", "default": null, "conditions": [], "min_value": 8, "max_value": 32, "step": 4, "sampling": "linear"}}, {"class_name": "Float", "config": {"name": "densedrop", "default": 0.3, "conditions": [], "min_value": 0.3, "max_value": 0.7, "step": null, "sampling": "log"}}, {"class_name": "Float", "config": {"name": "lr", "default": 0.001, "conditions": [], "min_value": 0.001, "max_value": 0.3, "step": null, "sampling": "log"}}, {"class_name": "Float", "config": {"name": "momentum", "default": 0.001, "conditions": [], "min_value": 0.001, "max_value": 0.5, "step": null, "sampling": "log"}}], "values": {"indrop": 0.173638138619595, "inner_layers": 1, "inner_neurons": 24, "densedrop": 0.5857208548877954, "lr": 0.06526719837643465, "momentum": 0.014865958494931693}}, "metrics": {"metrics": {"loss": {"direction": "min", "observations": [{"value": [1.127835762500763], "step": 8}]}, "categorical_accuracy": {"direction": "max", "observations": [{"value": [0.5465517222881318], "step": 8}]}, "macro_f1": {"direction": "min", "observations": [{"value": [0.3672287553548813], "step": 8}]}, "micro_f1": {"direction": "min", "observations": [{"value": [0.5465517222881318], "step": 8}]}, "val_loss": {"direction": "min", "observations": [{"value": [1.3301455855369568], "step": 8}]}, "val_categorical_accuracy": {"direction": "max", "observations": [{"value": [0.45652174651622773], "step": 8}]}, "val_macro_f1": {"direction": "min", "observations": [{"value": [0.356643995642662], "step": 8}]}, "val_micro_f1": {"direction": "min", "observations": [{"value": [0.45652174651622773], "step": 8}]}}}, "score": 0.5465517222881318, "best_step": 8, "status": "COMPLETED", "message": null}